bgapi/__init__.py
bgapi/apihelper.py
bgapi/apiparser.py
bgapi/bglib.py
bgapi/connector.py
bgapi/cpcconnector.py
bgapi/robustconnector.py
bgapi/serdeser.py
bgapi/serialconnector.py
bgapi/socketconnector.py
pybgapi-1.3.0.data/data/CHANGELOG.md
pybgapi-1.3.0.dist-info/LICENSE
pybgapi-1.3.0.dist-info/METADATA
pybgapi-1.3.0.dist-info/WHEEL
pybgapi-1.3.0.dist-info/top_level.txt
pybgapi-1.3.0.dist-info/RECORD
