Metadata-Version: 2.1
Name: pybgapi
Version: 1.3.0
Summary: Python interface for the BGAPI binary protocol
Home-page: https://github.com/SiliconLabs/pybgapi
Author: Silicon Labs
License: zlib
Platform: UNKNOWN
Classifier: License :: OSI Approved :: zlib/libpng License
Classifier: Programming Language :: Python :: 3
Classifier: Programming Language :: Python :: 3.7
Classifier: Programming Language :: Python :: 3.8
Classifier: Programming Language :: Python :: 3.9
Classifier: Programming Language :: Python :: 3.10
Classifier: Programming Language :: Python :: 3.11
Classifier: Programming Language :: Python :: 3.12
Requires-Python: >=3.7
License-File: LICENSE
Requires-Dist: pyserial
